srtedit/__init__.py
srtedit/__main__.py
srtedit/cli.py
srtedit/subtitle.py
srtedit/utils.py
srtedit-0.2.0.dist-info/LICENSE
srtedit-0.2.0.dist-info/METADATA
srtedit-0.2.0.dist-info/WHEEL
srtedit-0.2.0.dist-info/entry_points.txt
srtedit-0.2.0.dist-info/RECORD
