Metadata-Version: 2.3
Name: srtedit
Version: 0.2.0
Summary: 
Author: viown
Author-email: 48097677+viown@users.noreply.github.com
Requires-Python: >=3.11,<4.0
Classifier: Programming Language :: Python :: 3
Classifier: Programming Language :: Python :: 3.11
Classifier: Programming Language :: Python :: 3.12
Classifier: Programming Language :: Python :: 3.13
Requires-Dist: click (>=8.1.7,<9.0.0)
Requires-Dist: srt (>=3.5.3,<4.0.0)
